live_trading_indicators/__init__.py
live_trading_indicators/cast_input_params.py
live_trading_indicators/config.py
live_trading_indicators/constants.py
live_trading_indicators/exceptions.py
live_trading_indicators/indicator_data.py
live_trading_indicators/move_average.py
live_trading_indicators/plotting.py
live_trading_indicators/timeframe.py
live_trading_indicators/volume_clusters.py
live_trading_indicators/datasources/__init__.py
live_trading_indicators/datasources/bars_cache.py
live_trading_indicators/datasources/binance.py
live_trading_indicators/datasources/blocks_cache.py
live_trading_indicators/datasources/ccxt.py
live_trading_indicators/datasources/online_source.py
live_trading_indicators/datasources/sqlite_cache.py
live_trading_indicators/indicators_set/ADL.py
live_trading_indicators/indicators_set/ADX.py
live_trading_indicators/indicators_set/ATR.py
live_trading_indicators/indicators_set/Aroon.py
live_trading_indicators/indicators_set/Awesome.py
live_trading_indicators/indicators_set/BollingerBands.py
live_trading_indicators/indicators_set/CCI.py
live_trading_indicators/indicators_set/Chandelier.py
live_trading_indicators/indicators_set/EMA.py
live_trading_indicators/indicators_set/Ichimoku.py
live_trading_indicators/indicators_set/Keltner.py
live_trading_indicators/indicators_set/MA.py
live_trading_indicators/indicators_set/MACD.py
live_trading_indicators/indicators_set/MFI.py
live_trading_indicators/indicators_set/OBV.py
live_trading_indicators/indicators_set/OHLCV.py
live_trading_indicators/indicators_set/OHLCVM.py
live_trading_indicators/indicators_set/ParabolicSAR.py
live_trading_indicators/indicators_set/ROC.py
live_trading_indicators/indicators_set/RSI.py
live_trading_indicators/indicators_set/SMA.py
live_trading_indicators/indicators_set/Stochastic.py
live_trading_indicators/indicators_set/Supertrend.py
live_trading_indicators/indicators_set/TEMA.py
live_trading_indicators/indicators_set/TRIX.py
live_trading_indicators/indicators_set/VWAP.py
live_trading_indicators-0.7.5.dist-info/LICENSE
live_trading_indicators-0.7.5.dist-info/METADATA
live_trading_indicators-0.7.5.dist-info/WHEEL
live_trading_indicators-0.7.5.dist-info/top_level.txt
live_trading_indicators-0.7.5.dist-info/RECORD
