Metadata-Version: 2.1
Name: live-trading-indicators
Version: 0.7.5
Summary: A package for obtaining quotation data from various sources and saving them to a database. Quotes can be quickly extracted and used for calculations and forecasts. It is possible to receive and process data in real time. There are a significant number of ready-to-use indicators. The integrity of the data stored in the database is carefully monitored.
Home-page: https://github.com/hal9000cc/live_trading_indicators
Author: Aleksandr Kuznetsov
Author-email: hal@hal9000.cc
Classifier: Programming Language :: Python
Classifier: Programming Language :: Python :: 3
Classifier: Programming Language :: Python :: 3.10
Classifier: Programming Language :: Python :: 3.9
Classifier: Programming Language :: Python :: 3.8
Classifier: Programming Language :: Python :: 3.7
Classifier: License :: OSI Approved :: MIT License
Classifier: Operating System :: OS Independent
Classifier: Development Status :: 4 - Beta
Classifier: Topic :: Office/Business :: Financial :: Investment
Requires-Python: >=3.7
License-File: LICENSE
Requires-Dist: construct (<=2.10.0)
Requires-Dist: numba (<=0.56.3)
Requires-Dist: lz4 (<=4.3.2)
